topicminer/__init__.py
topicminer/auth.py
topicminer/core.py
topicminer/visuals.py
topicminer_louati-0.1.2.dist-info/METADATA
topicminer_louati-0.1.2.dist-info/WHEEL
topicminer_louati-0.1.2.dist-info/top_level.txt
topicminer_louati-0.1.2.dist-info/RECORD
